mikk/Logger.py
mikk/__init__.py
mikk/fmt.py
mikk/jsonc.py
mikk-0.1.dist-info/METADATA
mikk-0.1.dist-info/WHEEL
mikk-0.1.dist-info/top_level.txt
mikk-0.1.dist-info/RECORD
